get_chat_plus_in_bale/__init__.py
get_chat_plus_in_bale/chat_types.py
get_chat_plus_in_bale/get_chat.py
get_chat_plus_in_bale-1.0.0.dist-info/licenses/LICENSE
get_chat_plus_in_bale-1.0.0.dist-info/METADATA
get_chat_plus_in_bale-1.0.0.dist-info/WHEEL
get_chat_plus_in_bale-1.0.0.dist-info/top_level.txt
get_chat_plus_in_bale-1.0.0.dist-info/RECORD
