Metadata-Version: 2.4
Name: get_chat_plus_in_bale
Version: 1.0.0
Summary: get_chat_plus_in_bale . 🐍✨
Author: MohammadReza
Author-email: narnama.room@gmail.com
Project-URL: صفحه من ❤️, https://apicode.pythonanywhere.com/
Classifier: Programming Language :: Python :: 3
Classifier: License :: OSI Approved :: MIT License
Classifier: Operating System :: OS Independent
Requires-Python: >=3.5
License-File: LICENSE
Requires-Dist: requests
Requires-Dist: beautifulsoup4
Requires-Dist: aiohttp
Dynamic: author
Dynamic: author-email
Dynamic: classifier
Dynamic: description-content-type
Dynamic: license-file
Dynamic: project-url
Dynamic: requires-dist
Dynamic: requires-python
Dynamic: summary
